toynlp/__init__.py
toynlp/nnlm/__init__.py
toynlp/nnlm/config.py
toynlp/nnlm/inference.py
toynlp/nnlm/model.py
toynlp/nnlm/tokenizer.py
toynlp/nnlm/train.py
toynlp/paths.py
toynlp/py.typed
toynlp/seq2seq/__init__.py
toynlp/seq2seq/config.py
toynlp/seq2seq/dataset.py
toynlp/seq2seq/evaluation.py
toynlp/seq2seq/inference.py
toynlp/seq2seq/model.py
toynlp/seq2seq/tokenizer.py
toynlp/seq2seq/train.py
toynlp/util.py
toynlp/word2vec/README.md
toynlp/word2vec/__init__.py
toynlp/word2vec/config.py
toynlp/word2vec/dataset.py
toynlp/word2vec/hub.py
toynlp/word2vec/inference.py
toynlp/word2vec/model.py
toynlp/word2vec/tokenizer.py
toynlp/word2vec/train.py
toynlp-0.2.0.dist-info/WHEEL
toynlp-0.2.0.dist-info/METADATA
toynlp-0.2.0.dist-info/RECORD
